[{"post_title":"Emotional metal with melodic breaks","post_upvotes":1,"post_downvotes":0,"post_score":1,"post_id":"18ror55","youtube_url":"https:\/\/www.youtube.com\/watch?v=tymWpEU8wpM","comment_upvotes":1,"comment_downvotes":0,"comment_score":1,"comment_id":"kf2h4xq","music4all_youtube_id":"QwfP0iTaNTiv5e2w"},{"post_title":"Looking for something similar to Magdalena Bay's Mercurial World","post_upvotes":8,"post_downvotes":0,"post_score":8,"post_id":"18m5i2u","youtube_url":"https:\/\/www.youtube.com\/watch?v=Tv9YoYCKNoE","comment_upvotes":1,"comment_downvotes":0,"comment_score":1,"comment_id":"ke4qmx1","music4all_youtube_id":"1X5i4UWJuAOZAMUr"},{"post_title":"Shoegaze with female singer?","post_upvotes":5,"post_downvotes":0,"post_score":5,"post_id":"18ih3m7","youtube_url":"https:\/\/www.youtube.com\/watch?v=fIY64norZqY","comment_upvotes":1,"comment_downvotes":0,"comment_score":1,"comment_id":"kddphw6","music4all_youtube_id":"hYgQzjlwat3xyNK8"},{"post_title":"Looking for any love songs","post_upvotes":2,"post_downvotes":0,"post_score":2,"post_id":"18iiyc4","youtube_url":"https:\/\/www.youtube.com\/watch?v=p62rfWxs6a8","comment_upvotes":2,"comment_downvotes":0,"comment_score":2,"comment_id":"kddnjg9","music4all_youtube_id":"ETwuGNnkTlhp0IEs"},{"post_title":"I\u2019m looking for songs that aren\u2019t about romance \/ breakups \/ heartbreak, that also aren\u2019t super upbeat \/ overly positive.","post_upvotes":2,"post_downvotes":0,"post_score":2,"post_id":"18i53hj","youtube_url":"https:\/\/www.youtube.com\/watch?v=8j741TUIET0","comment_upvotes":1,"comment_downvotes":0,"comment_score":1,"comment_id":"kde6cbf","music4all_youtube_id":"C9IzTlAKsO7hI2aK"},{"post_title":"suggest some songs\/playlists\/albums\/artists with this kinda cozy vibe!","post_upvotes":24,"post_downvotes":0,"post_score":24,"post_id":"18hn4xq","youtube_url":"https:\/\/www.youtube.com\/watch?v=5tZlu4wP4pw","comment_upvotes":2,"comment_downvotes":0,"comment_score":2,"comment_id":"kd8uhpn","music4all_youtube_id":"2Ow0RJHAUNUBDwIq"}]